README.md
setup.py
drf_typed_views.egg-info/PKG-INFO
drf_typed_views.egg-info/SOURCES.txt
drf_typed_views.egg-info/dependency_links.txt
drf_typed_views.egg-info/top_level.txt
rest_typed_views/__init__.py
rest_typed_views/decorators.py
rest_typed_views/param_settings.py
rest_typed_views/params.py
rest_typed_views/utils.py
rest_typed_views/validators/__init__.py
rest_typed_views/validators/current_user_validator.py
rest_typed_views/validators/default_validator.py
rest_typed_views/validators/marshmallow_validator.py
rest_typed_views/validators/pydantic_validator.py
rest_typed_views/validators/type_system_validator.py
rest_typed_views/validators/validator_factory.py