Metadata-Version: 2.1
Name: drf-typed-views
Version: 0.2.0
Summary: Use type annotations for automatic request validation in Django REST Framework
Home-page: https://github.com/rsinger86/drf-typed-views
Author: Robert Singer
Author-email: robertgsinger@gmail.com
License: MIT
Keywords: django rest type annotations automatic validation validate
Platform: UNKNOWN
Classifier: Development Status :: 4 - Beta
Classifier: License :: OSI Approved :: MIT License
Classifier: Programming Language :: Python :: 3.3
Classifier: Programming Language :: Python :: 3.4
Classifier: Programming Language :: Python :: 3.5
Classifier: Programming Language :: Python :: 3.6
